[
  {
    "id": "6161697e8d8eecf791115271",
    "positionName": "consequat id",
    "companyName": "consectetur ex excepteur",
    "durationDay": 964,
    "durationDayText": "",
    "imageUrl": "https://i.picsum.photos/id/65/100/100.jpg?hmac=4JhYd-W819cbTJ5w1vTDVFZ0dl1sawch10ZbsH91",
    "distance": 0.41,
    "latitude": 41.008182,
    "longitude": 28.878181,
    "cityName": "İstanbul",
    "townName": "anim Mahallesi"
  },
  {
    "id": "6161697ef288836f836425f1",
    "positionName": "qui pariatur",
    "companyName": "nostrud proident mollit",
    "durationDay": 45,
    "durationDayText": "",
    "imageUrl": "https://i.picsum.photos/id/1012/100/100.jpg?hmac=vuow0o9zubuAYNA_nZKuHb055Vy6pf6df8dUXl-6F2Y",
    "distance": 6.95,
    "latitude": 37.03812,
    "longitude": null,
    "cityName": "İstanbul",
    "townName": "ipsum Mahallesi"
  },
  {
    "id": "6161697e442f0e262c8f0f19",
    "positionName": "consequat nulla",
    "companyName": "ullamco consequat ut",
    "durationDay": 124,
    "durationDayText": "",
    "imageUrl": "https://i.picsum.photos/id/981/100/100.jpg?hmac=cWCYgcyQ-L4ZyRiGPpOcIMFYVY3z_L7dT13gvR0HxwU",
    "distance": 13.93,
    "latitude": 41.007212,
    "longitude": 29.045734,
    "cityName": "İstanbul",
    "townName": "dolore Mahallesi"
  },
  {
    "id": "6161697e08cee06a64b6d51a",
    "positionName": "ex magna",
    "companyName": "nisi aliquip laborum",
    "durationDay": 279,
    "durationDayText": "",
    "imageUrl": "https://i.picsum.photos/id/741/100/100.jpg?hmac=kBdUTMwOzY2g8WKNAn0_fzHloBsigct4avRbz9SWnDE",
    "distance": 0.74,
    "latitude": null,
    "longitude": 38.003796,
    "cityName": "İstanbul",
    "townName": "id Mahallesi"
  },
  {
    "id": "6161697e933a10899d09ca2f",
    "positionName": "non reprehenderit",
    "companyName": "laboris anim officia",
    "durationDay": 15,
    "durationDayText": "",
    "imageUrl": "https://i.picsum.photos/id/1043/100/100.jpg?hmac=d4MsTGABpvomYb1Hmmfup4SJoHc6YMfef_hds1NPfIc",
    "distance": 0.34,
    "latitude": 41.045772,
    "longitude": 29.021988,
    "cityName": "İstanbul",
    "townName": "excepteur Mahallesi"
  },
  {
    "id": "6161697e31f75e9c63b2576b",
    "positionName": "dolor labore",
    "companyName": "mollit anim sint",
    "durationDay": 1,
    "durationDayText": "",
    "imageUrl": "https://i.picsum.photos/id/834/100/100.jpg?hmac=Y2nEM6T8UXx3C3oBLqJhcCLp0RACxjmHgA6DhNZhFBU",
    "distance": 4.74,
    "latitude": null,
    "longitude": null,
    "cityName": "İstanbul",
    "townName": "qui Mahallesi"
  },
  {
    "id": "6161697ef84698a45a952145",
    "positionName": "dolor aliqua",
    "companyName": "incididunt irure est",
    "durationDay": 0,
    "durationDayText": "",
    "imageUrl": "https://i.picsum.photos/id/684/100/100.jpg?hmac=LqKwzgn2hb70Ii4Vjk9pLmOKQfeM5AtO9HH_6H9NsYE",
    "distance": 6.78,
    "latitude": 41.041907,
    "longitude": 29.039886,
    "cityName": "İstanbul",
    "townName": "non Mahallesi"
  },
  {
    "id": "6161697e8d8eecf791115271",
    "positionName": "consequat id",
    "companyName": "consectetur ex excepteur",
    "durationDay": 964,
    "durationDayText": "",
    "imageUrl": "https://i.picsum.photos/id/65/100/100.jpg?hmac=4JhYd-W819cbTJ5w1vTDVFZ0dl1sawch10ZbsH91",
    "distance": 0.41,
    "latitude": 41.008182,
    "longitude": 28.878181,
    "cityName": "İstanbul",
    "townName": "anim Mahallesi"
  },
  {
    "id": "6161697ef288836f836425f1",
    "positionName": "qui pariatur",
    "companyName": "nostrud proident mollit",
    "durationDay": 45,
    "durationDayText": "",
    "imageUrl": "https://i.picsum.photos/id/1012/100/100.jpg?hmac=vuow0o9zubuAYNA_nZKuHb055Vy6pf6df8dUXl-6F2Y",
    "distance": 6.95,
    "latitude": 37.03812,
    "longitude": null,
    "cityName": "İstanbul",
    "townName": "ipsum Mahallesi"
  },
  {
    "id": "6161697e442f0e262c8f0f19",
    "positionName": "consequat nulla",
    "companyName": "ullamco consequat ut",
    "durationDay": 124,
    "durationDayText": "",
    "imageUrl": "https://i.picsum.photos/id/981/100/100.jpg?hmac=cWCYgcyQ-L4ZyRiGPpOcIMFYVY3z_L7dT13gvR0HxwU",
    "distance": 13.93,
    "latitude": 41.007212,
    "longitude": 29.045734,
    "cityName": "İstanbul",
    "townName": "dolore Mahallesi"
  },
  {
    "id": "6161697e08cee06a64b6d51a",
    "positionName": "ex magna",
    "companyName": "nisi aliquip laborum",
    "durationDay": 279,
    "durationDayText": "",
    "imageUrl": "https://i.picsum.photos/id/741/100/100.jpg?hmac=kBdUTMwOzY2g8WKNAn0_fzHloBsigct4avRbz9SWnDE",
    "distance": 0.74,
    "latitude": null,
    "longitude": 38.003796,
    "cityName": "İstanbul",
    "townName": "id Mahallesi"
  },
  {
    "id": "6161697e933a10899d09ca2f",
    "positionName": "non reprehenderit",
    "companyName": "laboris anim officia",
    "durationDay": 15,
    "durationDayText": "",
    "imageUrl": "https://i.picsum.photos/id/1043/100/100.jpg?hmac=d4MsTGABpvomYb1Hmmfup4SJoHc6YMfef_hds1NPfIc",
    "distance": 0.34,
    "latitude": 41.045772,
    "longitude": 29.021988,
    "cityName": "İstanbul",
    "townName": "excepteur Mahallesi"
  },
  {
    "id": "6161697e31f75e9c63b2576b",
    "positionName": "dolor labore",
    "companyName": "mollit anim sint",
    "durationDay": 1,
    "durationDayText": "",
    "imageUrl": "https://i.picsum.photos/id/834/100/100.jpg?hmac=Y2nEM6T8UXx3C3oBLqJhcCLp0RACxjmHgA6DhNZhFBU",
    "distance": 4.74,
    "latitude": null,
    "longitude": null,
    "cityName": "İstanbul",
    "townName": "qui Mahallesi"
  },
  {
    "id": "6161697ef84698a45a952145",
    "positionName": "dolor aliqua",
    "companyName": "incididunt irure est",
    "durationDay": 0,
    "durationDayText": "",
    "imageUrl": "https://i.picsum.photos/id/684/100/100.jpg?hmac=LqKwzgn2hb70Ii4Vjk9pLmOKQfeM5AtO9HH_6H9NsYE",
    "distance": 6.78,
    "latitude": 41.041907,
    "longitude": 29.039886,
    "cityName": "İstanbul",
    "townName": "non Mahallesi"
  },
  {
    "id": "6161697e8d8eecf791115271",
    "positionName": "consequat id",
    "companyName": "consectetur ex excepteur",
    "durationDay": 964,
    "durationDayText": "",
    "imageUrl": "https://i.picsum.photos/id/65/100/100.jpg?hmac=4JhYd-W819cbTJ5w1vTDVFZ0dl1sawch10ZbsH91",
    "distance": 0.41,
    "latitude": 41.008182,
    "longitude": 28.878181,
    "cityName": "İstanbul",
    "townName": "anim Mahallesi"
  },
  {
    "id": "6161697ef288836f836425f1",
    "positionName": "qui pariatur",
    "companyName": "nostrud proident mollit",
    "durationDay": 45,
    "durationDayText": "",
    "imageUrl": "https://i.picsum.photos/id/1012/100/100.jpg?hmac=vuow0o9zubuAYNA_nZKuHb055Vy6pf6df8dUXl-6F2Y",
    "distance": 6.95,
    "latitude": 37.03812,
    "longitude": null,
    "cityName": "İstanbul",
    "townName": "ipsum Mahallesi"
  },
  {
    "id": "6161697e442f0e262c8f0f19",
    "positionName": "consequat nulla",
    "companyName": "ullamco consequat ut",
    "durationDay": 124,
    "durationDayText": "",
    "imageUrl": "https://i.picsum.photos/id/981/100/100.jpg?hmac=cWCYgcyQ-L4ZyRiGPpOcIMFYVY3z_L7dT13gvR0HxwU",
    "distance": 13.93,
    "latitude": 41.007212,
    "longitude": 29.045734,
    "cityName": "İstanbul",
    "townName": "dolore Mahallesi"
  },
  {
    "id": "6161697e08cee06a64b6d51a",
    "positionName": "ex magna",
    "companyName": "nisi aliquip laborum",
    "durationDay": 279,
    "durationDayText": "",
    "imageUrl": "https://i.picsum.photos/id/741/100/100.jpg?hmac=kBdUTMwOzY2g8WKNAn0_fzHloBsigct4avRbz9SWnDE",
    "distance": 0.74,
    "latitude": null,
    "longitude": 38.003796,
    "cityName": "İstanbul",
    "townName": "id Mahallesi"
  },
  {
    "id": "6161697e933a10899d09ca2f",
    "positionName": "non reprehenderit",
    "companyName": "laboris anim officia",
    "durationDay": 15,
    "durationDayText": "",
    "imageUrl": "https://i.picsum.photos/id/1043/100/100.jpg?hmac=d4MsTGABpvomYb1Hmmfup4SJoHc6YMfef_hds1NPfIc",
    "distance": 0.34,
    "latitude": 41.045772,
    "longitude": 29.021988,
    "cityName": "İstanbul",
    "townName": "excepteur Mahallesi"
  },
  {
    "id": "6161697e31f75e9c63b2576b",
    "positionName": "dolor labore",
    "companyName": "mollit anim sint",
    "durationDay": 1,
    "durationDayText": "",
    "imageUrl": "https://i.picsum.photos/id/834/100/100.jpg?hmac=Y2nEM6T8UXx3C3oBLqJhcCLp0RACxjmHgA6DhNZhFBU",
    "distance": 4.74,
    "latitude": null,
    "longitude": null,
    "cityName": "İstanbul",
    "townName": "qui Mahallesi"
  },
  {
    "id": "6161697ef84698a45a952145",
    "positionName": "dolor aliqua",
    "companyName": "incididunt irure est",
    "durationDay": 0,
    "durationDayText": "",
    "imageUrl": "https://i.picsum.photos/id/684/100/100.jpg?hmac=LqKwzgn2hb70Ii4Vjk9pLmOKQfeM5AtO9HH_6H9NsYE",
    "distance": 6.78,
    "latitude": 41.041907,
    "longitude": 29.039886,
    "cityName": "İstanbul",
    "townName": "non Mahallesi"
  },
  {
    "id": "6161697e8d8eecf791115271",
    "positionName": "consequat id",
    "companyName": "consectetur ex excepteur",
    "durationDay": 964,
    "durationDayText": "",
    "imageUrl": "https://i.picsum.photos/id/65/100/100.jpg?hmac=4JhYd-W819cbTJ5w1vTDVFZ0dl1sawch10ZbsH91",
    "distance": 0.41,
    "latitude": 41.008182,
    "longitude": 28.878181,
    "cityName": "İstanbul",
    "townName": "anim Mahallesi"
  },
  {
    "id": "6161697ef288836f836425f1",
    "positionName": "qui pariatur",
    "companyName": "nostrud proident mollit",
    "durationDay": 45,
    "durationDayText": "",
    "imageUrl": "https://i.picsum.photos/id/1012/100/100.jpg?hmac=vuow0o9zubuAYNA_nZKuHb055Vy6pf6df8dUXl-6F2Y",
    "distance": 6.95,
    "latitude": 37.03812,
    "longitude": null,
    "cityName": "İstanbul",
    "townName": "ipsum Mahallesi"
  },
  {
    "id": "6161697e442f0e262c8f0f19",
    "positionName": "consequat nulla",
    "companyName": "ullamco consequat ut",
    "durationDay": 124,
    "durationDayText": "",
    "imageUrl": "https://i.picsum.photos/id/981/100/100.jpg?hmac=cWCYgcyQ-L4ZyRiGPpOcIMFYVY3z_L7dT13gvR0HxwU",
    "distance": 13.93,
    "latitude": 41.007212,
    "longitude": 29.045734,
    "cityName": "İstanbul",
    "townName": "dolore Mahallesi"
  },
  {
    "id": "6161697e08cee06a64b6d51a",
    "positionName": "ex magna",
    "companyName": "nisi aliquip laborum",
    "durationDay": 279,
    "durationDayText": "",
    "imageUrl": "https://i.picsum.photos/id/741/100/100.jpg?hmac=kBdUTMwOzY2g8WKNAn0_fzHloBsigct4avRbz9SWnDE",
    "distance": 0.74,
    "latitude": null,
    "longitude": 38.003796,
    "cityName": "İstanbul",
    "townName": "id Mahallesi"
  },
  {
    "id": "6161697e933a10899d09ca2f",
    "positionName": "non reprehenderit",
    "companyName": "laboris anim officia",
    "durationDay": 15,
    "durationDayText": "",
    "imageUrl": "https://i.picsum.photos/id/1043/100/100.jpg?hmac=d4MsTGABpvomYb1Hmmfup4SJoHc6YMfef_hds1NPfIc",
    "distance": 0.34,
    "latitude": 41.045772,
    "longitude": 29.021988,
    "cityName": "İstanbul",
    "townName": "excepteur Mahallesi"
  },
  {
    "id": "6161697e31f75e9c63b2576b",
    "positionName": "dolor labore",
    "companyName": "mollit anim sint",
    "durationDay": 1,
    "durationDayText": "",
    "imageUrl": "https://i.picsum.photos/id/834/100/100.jpg?hmac=Y2nEM6T8UXx3C3oBLqJhcCLp0RACxjmHgA6DhNZhFBU",
    "distance": 4.74,
    "latitude": null,
    "longitude": null,
    "cityName": "İstanbul",
    "townName": "qui Mahallesi"
  },
  {
    "id": "6161697ef84698a45a952145",
    "positionName": "dolor aliqua",
    "companyName": "incididunt irure est",
    "durationDay": 0,
    "durationDayText": "",
    "imageUrl": "https://i.picsum.photos/id/684/100/100.jpg?hmac=LqKwzgn2hb70Ii4Vjk9pLmOKQfeM5AtO9HH_6H9NsYE",
    "distance": 6.78,
    "latitude": 41.041907,
    "longitude": 29.039886,
    "cityName": "İstanbul",
    "townName": "non Mahallesi"
  },
  {
    "id": "6161697e8d8eecf791115271",
    "positionName": "consequat id",
    "companyName": "consectetur ex excepteur",
    "durationDay": 964,
    "durationDayText": "",
    "imageUrl": "https://i.picsum.photos/id/65/100/100.jpg?hmac=4JhYd-W819cbTJ5w1vTDVFZ0dl1sawch10ZbsH91",
    "distance": 0.41,
    "latitude": 41.008182,
    "longitude": 28.878181,
    "cityName": "İstanbul",
    "townName": "anim Mahallesi"
  },
  {
    "id": "6161697ef288836f836425f1",
    "positionName": "qui pariatur",
    "companyName": "nostrud proident mollit",
    "durationDay": 45,
    "durationDayText": "",
    "imageUrl": "https://i.picsum.photos/id/1012/100/100.jpg?hmac=vuow0o9zubuAYNA_nZKuHb055Vy6pf6df8dUXl-6F2Y",
    "distance": 6.95,
    "latitude": 37.03812,
    "longitude": null,
    "cityName": "İstanbul",
    "townName": "ipsum Mahallesi"
  },
  {
    "id": "6161697e442f0e262c8f0f19",
    "positionName": "consequat nulla",
    "companyName": "ullamco consequat ut",
    "durationDay": 124,
    "durationDayText": "",
    "imageUrl": "https://i.picsum.photos/id/981/100/100.jpg?hmac=cWCYgcyQ-L4ZyRiGPpOcIMFYVY3z_L7dT13gvR0HxwU",
    "distance": 13.93,
    "latitude": 41.007212,
    "longitude": 29.045734,
    "cityName": "İstanbul",
    "townName": "dolore Mahallesi"
  },
  {
    "id": "6161697e08cee06a64b6d51a",
    "positionName": "ex magna",
    "companyName": "nisi aliquip laborum",
    "durationDay": 279,
    "durationDayText": "",
    "imageUrl": "https://i.picsum.photos/id/741/100/100.jpg?hmac=kBdUTMwOzY2g8WKNAn0_fzHloBsigct4avRbz9SWnDE",
    "distance": 0.74,
    "latitude": null,
    "longitude": 38.003796,
    "cityName": "İstanbul",
    "townName": "id Mahallesi"
  },
  {
    "id": "6161697e933a10899d09ca2f",
    "positionName": "non reprehenderit",
    "companyName": "laboris anim officia",
    "durationDay": 15,
    "durationDayText": "",
    "imageUrl": "https://i.picsum.photos/id/1043/100/100.jpg?hmac=d4MsTGABpvomYb1Hmmfup4SJoHc6YMfef_hds1NPfIc",
    "distance": 0.34,
    "latitude": 41.045772,
    "longitude": 29.021988,
    "cityName": "İstanbul",
    "townName": "excepteur Mahallesi"
  },
  {
    "id": "6161697e31f75e9c63b2576b",
    "positionName": "dolor labore",
    "companyName": "mollit anim sint",
    "durationDay": 1,
    "durationDayText": "",
    "imageUrl": "https://i.picsum.photos/id/834/100/100.jpg?hmac=Y2nEM6T8UXx3C3oBLqJhcCLp0RACxjmHgA6DhNZhFBU",
    "distance": 4.74,
    "latitude": null,
    "longitude": null,
    "cityName": "İstanbul",
    "townName": "qui Mahallesi"
  },
  {
    "id": "6161697ef84698a45a952145",
    "positionName": "dolor aliqua",
    "companyName": "incididunt irure est",
    "durationDay": 0,
    "durationDayText": "",
    "imageUrl": "https://i.picsum.photos/id/684/100/100.jpg?hmac=LqKwzgn2hb70Ii4Vjk9pLmOKQfeM5AtO9HH_6H9NsYE",
    "distance": 6.78,
    "latitude": 41.041907,
    "longitude": 29.039886,
    "cityName": "İstanbul",
    "townName": "non Mahallesi"
  }
]
